tiimaweb/__init__.py
tiimaweb/__main__.py
tiimaweb/cli.py
tiimaweb/client.py
tiimaweb/exceptions.py
tiimaweb/types.py
tiimaweb-0.4.0.dist-info/entry_points.txt
tiimaweb-0.4.0.dist-info/LICENSE
tiimaweb-0.4.0.dist-info/WHEEL
tiimaweb-0.4.0.dist-info/METADATA
tiimaweb-0.4.0.dist-info/RECORD
