Metadata-Version: 2.1
Name: tiimaweb
Version: 0.4.0
Summary: Tiima Web Controller
Home-page: https://github.com/suutari/tiimaweb
License: MIT
Author: Tuomas Suutari
Author-email: tuomas@nepnep.net
Requires-Python: >=2.7, !=3.0.*, !=3.1.*, !=3.2.*, !=3.3.*, !=3.4.*
Classifier: License :: OSI Approved :: MIT License
Classifier: Programming Language :: Python :: 2
Classifier: Programming Language :: Python :: 2.7
Classifier: Programming Language :: Python :: 3
Classifier: Programming Language :: Python :: 3.5
Classifier: Programming Language :: Python :: 3.6
Classifier: Programming Language :: Python :: 3.7
Classifier: Programming Language :: Python :: 3.8
Classifier: Programming Language :: Python :: 3.9
Requires-Dist: mechanicalsoup (>=0.12.0,<0.13.0)
Requires-Dist: pytz (>=2016.0)
Requires-Dist: typing; python_version < "3.5"
Project-URL: Repository, https://github.com/suutari/tiimaweb
